mikan/__init__.py
mikan/config.py
mikan/downloader.py
mikan/html_parser.py
mikan/json_utils.py
mikan/main.py
mikan/plugins/__init__.py
mikan/plugins/bandori.py
mikan/plugins/default.py
mikan/plugins/idolmaster.py
mikan/plugins/revue.py
mikan/plugins/sif.py
mikan/plugins/sif2.py
mikan/plugins/sifas.py
mikan/plugins/sifasstills.py
mikan/py.typed
mikan_card_downloader-3.2.0.dist-info/LICENSE
mikan_card_downloader-3.2.0.dist-info/METADATA
mikan_card_downloader-3.2.0.dist-info/WHEEL
mikan_card_downloader-3.2.0.dist-info/entry_points.txt
mikan_card_downloader-3.2.0.dist-info/RECORD
