Metadata-Version: 2.3
Name: mikan-card-downloader
Version: 3.2.0
Summary: Downloads cards and stills from SIFAS and SIF.
License: GPLv3
Keywords: sif,sifas,lovelive,mikan,downloader,bandori,bangdream,idolmaster,revuestarlight,imas
Author: DemonicSavage
Requires-Python: >=3.10,<4.0
Classifier: Development Status :: 5 - Production/Stable
Classifier: Environment :: Console
Classifier: Intended Audience :: End Users/Desktop
Classifier: License :: OSI Approved :: GNU General Public License v3 (GPLv3)
Classifier: License :: Other/Proprietary License
Classifier: Operating System :: OS Independent
Classifier: Programming Language :: Python :: 3
Classifier: Programming Language :: Python :: 3.10
Classifier: Programming Language :: Python :: 3.11
Classifier: Programming Language :: Python :: 3.12
Classifier: Programming Language :: Python :: 3.13
Classifier: Topic :: Games/Entertainment
Classifier: Topic :: Utilities
Requires-Dist: aiofiles (>=24.1.0,<25.0.0)
Requires-Dist: aiohttp[speedups] (>=3.9.0,<4.0.0)
Requires-Dist: beautifulsoup4 (>=4.11.1,<5.0.0)
Requires-Dist: lxml (>=5.0.0,<6.0.0)
Requires-Dist: platformdirs (>=4.0.0,<5.0.0)
Requires-Dist: tqdm (>=4.64.0,<5.0.0)
Project-URL: Homepage, https://www.demonicsavage.com/projects/mikan
Project-URL: Repository, https://github.com/demonicsavage/mikan
